ipysheet/__init__.py
ipysheet/_version.py
ipysheet/docutils.py
ipysheet/easy.py
ipysheet/numpy_loader.py
ipysheet/pandas_loader.py
ipysheet/serializer.py
ipysheet/sheet.py
ipysheet/test_all.py
ipysheet/utils.py
ipysheet/labextension/package.json
ipysheet/labextension/static/253.ca45efd495cd6a09cb13.js
ipysheet/labextension/static/273.f9126aed5b37ca9693c8.js
ipysheet/labextension/static/480.2bbf43eba8201505ade6.js
ipysheet/labextension/static/481.46a087fdaf5f82da098e.js
ipysheet/labextension/static/481.46a087fdaf5f82da098e.js.LICENSE.txt
ipysheet/labextension/static/568.7d6b116b394a6d7459ae.js
ipysheet/labextension/static/776.5a890f9c67be8a81b7fd.js
ipysheet/labextension/static/861.7532193a31afa3a7559f.js
ipysheet/labextension/static/861.7532193a31afa3a7559f.js.LICENSE.txt
ipysheet/labextension/static/remoteEntry.c686cffc67f506ae58df.js
ipysheet/labextension/static/style.js
ipysheet/labextension/static/third-party-licenses.json
ipysheet/static/extension.js
ipysheet/static/index.js
ipysheet/static/index.js.LICENSE.txt
ipysheet/static/index.js.map
ipysheet-0.7.0.data/data/etc/jupyter/nbconfig/notebook.d/ipysheet.json
ipysheet-0.7.0.data/data/share/jupyter/labextensions/ipysheet/install.json
ipysheet-0.7.0.data/data/share/jupyter/labextensions/ipysheet/package.json
ipysheet-0.7.0.data/data/share/jupyter/labextensions/ipysheet/static/253.ca45efd495cd6a09cb13.js
ipysheet-0.7.0.data/data/share/jupyter/labextensions/ipysheet/static/273.f9126aed5b37ca9693c8.js
ipysheet-0.7.0.data/data/share/jupyter/labextensions/ipysheet/static/480.2bbf43eba8201505ade6.js
ipysheet-0.7.0.data/data/share/jupyter/labextensions/ipysheet/static/481.46a087fdaf5f82da098e.js
ipysheet-0.7.0.data/data/share/jupyter/labextensions/ipysheet/static/481.46a087fdaf5f82da098e.js.LICENSE.txt
ipysheet-0.7.0.data/data/share/jupyter/labextensions/ipysheet/static/568.7d6b116b394a6d7459ae.js
ipysheet-0.7.0.data/data/share/jupyter/labextensions/ipysheet/static/776.5a890f9c67be8a81b7fd.js
ipysheet-0.7.0.dist-info/LICENSE
ipysheet-0.7.0.dist-info/METADATA
ipysheet-0.7.0.dist-info/WHEEL
ipysheet-0.7.0.dist-info/top_level.txt
ipysheet-0.7.0.dist-info/RECORD
