Metadata-Version: 2.1
Name: ipysheet
Version: 0.7.0
Summary: Spreadsheet in the Jupyter notebook.
Home-page: https://github.com/QuantStack/ipysheet
Author: Maarten A. Breddels
Author-email: michael.barry@gmo.com
License: MIT
Keywords: Jupyter,JupyterLab,JupyterLab3
Platform: Linux
Platform: Mac OS X
Platform: Windows
Classifier: License :: OSI Approved :: BSD License
Classifier: Programming Language :: Python
Classifier: Programming Language :: Python :: 3
Classifier: Programming Language :: Python :: 3.6
Classifier: Programming Language :: Python :: 3.7
Classifier: Programming Language :: Python :: 3.8
Classifier: Programming Language :: Python :: 3.9
Classifier: Framework :: Jupyter
Requires-Python: >=3.6
License-File: LICENSE
Requires-Dist: ipywidgets (<9.0,>=7.5.0)
